<?xml version="1.0" encoding="utf-8"?>
<Messages>
	<Message prefix="[HLS 200-10]" severity="INFO" keynum="HLS_10_1312" content="Analyzing design file &apos;final_conv2d/conv_v2/conv_v2.cpp&apos; ..." tag=""/>
	<Message prefix="[HLS 200-10]" severity="INFO" keynum="HLS_10_1465" content="Validating synthesis directives ..." tag=""/>
	<Message prefix="[HLS 200-111]" severity="INFO" keynum="473" content="Finished Checking Pragmas Time (s): cpu = 00:00:01 ; elapsed = 00:00:04 . Memory (MB): peak = 101.383 ; gain = 44.656" tag=""/>
	<Message prefix="[HLS 200-111]" severity="INFO" keynum="473" content="Finished Linking Time (s): cpu = 00:00:01 ; elapsed = 00:00:08 . Memory (MB): peak = 101.402 ; gain = 44.676" tag=""/>
	<Message prefix="[HLS 200-10]" severity="INFO" keynum="HLS_10_1467" content="Starting code transformations ..." tag=""/>
	<Message prefix="[HLS 200-111]" severity="INFO" keynum="473" content="Finished Standard Transforms Time (s): cpu = 00:00:01 ; elapsed = 00:00:08 . Memory (MB): peak = 103.387 ; gain = 46.660" tag=""/>
	<Message prefix="[HLS 200-10]" severity="INFO" keynum="HLS_10_1472" content="Checking synthesizability ..." tag=""/>
	<Message prefix="[XFORM 203-602]" severity="INFO" keynum="794" content="Inlining function &apos;bounds_ok&apos; into &apos;sum_window&apos; (final_conv2d/conv_v2/conv_v2.cpp:26) automatically." tag=""/>
	<Message prefix="[HLS 200-111]" severity="INFO" keynum="473" content="Finished Checking Synthesizability Time (s): cpu = 00:00:01 ; elapsed = 00:00:08 . Memory (MB): peak = 103.734 ; gain = 47.008" tag=""/>
	<Message prefix="[XFORM 203-502]" severity="INFO" keynum="812" content="Unrolling small iteration loop &apos;buf_y&apos; (final_conv2d/conv_v2/conv_v2.cpp:52) in function &apos;do_convolution&apos; automatically." tag=""/>
	<Message prefix="[XFORM 203-502]" severity="INFO" keynum="813" content="Unrolling all sub-loops inside loop &apos;for_x&apos; (final_conv2d/conv_v2/conv_v2.cpp:66) in function &apos;do_convolution&apos; for pipelining." tag=""/>
	<Message prefix="[XFORM 203-502]" severity="INFO" keynum="817" content="Unrolling all loops for pipelining in function &apos;sum_window&apos; (final_conv2d/conv_v2/conv_v2.cpp:18)." tag=""/>
	<Message prefix="[XFORM 203-501]" severity="INFO" keynum="891" content="Unrolling loop &apos;buf_y&apos; (final_conv2d/conv_v2/conv_v2.cpp:52) in function &apos;do_convolution&apos; completely." tag=""/>
	<Message prefix="[XFORM 203-501]" severity="INFO" keynum="891" content="Unrolling loop &apos;Loop-4.1.1&apos; (final_conv2d/conv_v2/conv_v2.cpp:75) in function &apos;do_convolution&apos; completely." tag=""/>
	<Message prefix="[XFORM 203-501]" severity="INFO" keynum="891" content="Unrolling loop &apos;Loop-4.1.2&apos; (final_conv2d/conv_v2/conv_v2.cpp:88) in function &apos;do_convolution&apos; completely." tag=""/>
	<Message prefix="[XFORM 203-501]" severity="INFO" keynum="891" content="Unrolling loop &apos;Loop-4.1.2.1&apos; (final_conv2d/conv_v2/conv_v2.cpp:89) in function &apos;do_convolution&apos; completely." tag=""/>
	<Message prefix="[XFORM 203-501]" severity="INFO" keynum="891" content="Unrolling loop &apos;Loop-4.1.3&apos; (final_conv2d/conv_v2/conv_v2.cpp:93) in function &apos;do_convolution&apos; completely." tag=""/>
	<Message prefix="[XFORM 203-501]" severity="INFO" keynum="891" content="Unrolling loop &apos;win_i&apos; (final_conv2d/conv_v2/conv_v2.cpp:23) in function &apos;sum_window&apos; completely." tag=""/>
	<Message prefix="[XFORM 203-501]" severity="INFO" keynum="891" content="Unrolling loop &apos;win_j&apos; (final_conv2d/conv_v2/conv_v2.cpp:25) in function &apos;sum_window&apos; completely." tag=""/>
	<Message prefix="[XFORM 203-101]" severity="INFO" keynum="692" content="Partitioning array &apos;line_buf&apos; (final_conv2d/conv_v2/conv_v2.cpp:39) in dimension 1 completely." tag=""/>
	<Message prefix="[XFORM 203-101]" severity="INFO" keynum="692" content="Partitioning array &apos;window&apos; (final_conv2d/conv_v2/conv_v2.cpp:40) in dimension 1 completely." tag=""/>
	<Message prefix="[XFORM 203-101]" severity="INFO" keynum="692" content="Partitioning array &apos;right&apos; (final_conv2d/conv_v2/conv_v2.cpp:41) in dimension 1 completely." tag=""/>
	<Message prefix="[XFORM 203-101]" severity="INFO" keynum="692" content="Partitioning array &apos;window&apos; (final_conv2d/conv_v2/conv_v2.cpp:40) in dimension 2 completely." tag=""/>
	<Message prefix="[XFORM 203-602]" severity="INFO" keynum="794" content="Inlining function &apos;bounds_ok&apos; into &apos;sum_window&apos; (final_conv2d/conv_v2/conv_v2.cpp:26) automatically." tag=""/>
	<Message prefix="[XFORM 203-401]" severity="INFO" keynum="809" content="Performing if-conversion on hyperblock to (final_conv2d/conv_v2/conv_v2.cpp:33:5) in function &apos;sum_window&apos;... converting 11 basic blocks." tag=""/>
	<Message prefix="[XFORM 203-401]" severity="INFO" keynum="809" content="Performing if-conversion on hyperblock from (final_conv2d/conv_v2/conv_v2.cpp:60:3) to (final_conv2d/conv_v2/conv_v2.cpp:58:50) in function &apos;do_convolution&apos;... converting 7 basic blocks." tag=""/>
	<Message prefix="[XFORM 203-602]" severity="INFO" keynum="794" content="Inlining function &apos;sum_window&apos; into &apos;do_convolution&apos; (final_conv2d/conv_v2/conv_v2.cpp:68) automatically." tag=""/>
	<Message prefix="[HLS 200-111]" severity="INFO" keynum="473" content="Finished Pre-synthesis Time (s): cpu = 00:00:01 ; elapsed = 00:00:09 . Memory (MB): peak = 124.945 ; gain = 68.219" tag=""/>
	<Message prefix="[XFORM 203-541]" severity="INFO" keynum="789" content="Flattening a loop nest &apos;win_y&apos; (final_conv2d/conv_v2/conv_v2.cpp:58:5) in function &apos;do_convolution&apos;." tag=""/>
	<Message prefix="[XFORM 203-541]" severity="INFO" keynum="789" content="Flattening a loop nest &apos;for_y&apos; (final_conv2d/conv_v2/conv_v2.cpp:64:4) in function &apos;do_convolution&apos;." tag=""/>
	<Message prefix="[HLS 200-111]" severity="INFO" keynum="473" content="Finished Architecture Synthesis Time (s): cpu = 00:00:01 ; elapsed = 00:00:09 . Memory (MB): peak = 124.945 ; gain = 68.219" tag=""/>
	<Message prefix="[HLS 200-10]" severity="INFO" keynum="HLS_10_1317" content="Starting hardware synthesis ..." tag=""/>
	<Message prefix="[HLS 200-10]" severity="INFO" keynum="HLS_10_1385" content="Synthesizing &apos;do_convolution&apos; ..." tag=""/>
	<Message prefix="[HLS 200-10]" severity="INFO" keynum="HLS_10_1477" content="----------------------------------------------------------------" tag=""/>
	<Message prefix="[HLS 200-42]" severity="INFO" keynum="HLS_42_1438" content="-- Implementing module &apos;do_convolution&apos;" tag=""/>
	<Message prefix="[HLS 200-10]" severity="INFO" keynum="HLS_10_1478" content="----------------------------------------------------------------" tag=""/>
	<Message prefix="[SCHED 204-11]" severity="INFO" keynum="139" content="Starting scheduling ..." tag=""/>
	<Message prefix="[SCHED 204-61]" severity="INFO" keynum="107" content="Pipelining loop &apos;buf_x1&apos;." tag=""/>
	<Message prefix="[SCHED 204-61]" severity="INFO" keynum="110" content="Pipelining result : Target II = 1, Final II = 1, Depth = 2." tag=""/>
	<Message prefix="[SCHED 204-61]" severity="INFO" keynum="107" content="Pipelining loop &apos;buf_x2&apos;." tag=""/>
	<Message prefix="[SCHED 204-61]" severity="INFO" keynum="110" content="Pipelining result : Target II = 1, Final II = 1, Depth = 2." tag=""/>
	<Message prefix="[SCHED 204-61]" severity="INFO" keynum="107" content="Pipelining loop &apos;win_y_win_x&apos;." tag=""/>
	<Message prefix="[SCHED 204-61]" severity="INFO" keynum="110" content="Pipelining result : Target II = 1, Final II = 1, Depth = 2." tag=""/>
	<Message prefix="[SCHED 204-61]" severity="INFO" keynum="107" content="Pipelining loop &apos;for_y_for_x&apos;." tag=""/>
	<Message prefix="[SCHED 204-61]" severity="INFO" keynum="110" content="Pipelining result : Target II = 1, Final II = 1, Depth = 5." tag=""/>
	<Message prefix="[SCHED 204-11]" severity="INFO" keynum="138" content="Finished scheduling." tag=""/>
	<Message prefix="[HLS 200-111]" severity="INFO" keynum="474" content=" Elapsed time: 9.565 seconds; current allocated memory: 76.898 MB." tag=""/>
	<Message prefix="[BIND 205-100]" severity="INFO" keynum="439" content="Starting micro-architecture generation ..." tag=""/>
	<Message prefix="[BIND 205-101]" severity="INFO" keynum="211" content="Performing variable lifetime analysis." tag=""/>
	<Message prefix="[BIND 205-101]" severity="INFO" keynum="210" content="Exploring resource sharing." tag=""/>
	<Message prefix="[BIND 205-101]" severity="INFO" keynum="206" content="Binding ..." tag=""/>
	<Message prefix="[BIND 205-100]" severity="INFO" keynum="438" content="Finished micro-architecture generation." tag=""/>
	<Message prefix="[HLS 200-111]" severity="INFO" keynum="474" content=" Elapsed time: 0.167 seconds; current allocated memory: 77.530 MB." tag=""/>
	<Message prefix="[HLS 200-10]" severity="INFO" keynum="HLS_10_1483" content="----------------------------------------------------------------" tag=""/>
	<Message prefix="[HLS 200-10]" severity="INFO" keynum="HLS_10_1484" content="-- Generating RTL for module &apos;do_convolution&apos;" tag=""/>
	<Message prefix="[HLS 200-10]" severity="INFO" keynum="HLS_10_1485" content="----------------------------------------------------------------" tag=""/>
	<Message prefix="[RTGEN 206-500]" severity="INFO" keynum="73" content="Setting interface mode on port &apos;do_convolution/out_stream_V&apos; to &apos;ap_fifo&apos;." tag=""/>
	<Message prefix="[RTGEN 206-500]" severity="INFO" keynum="73" content="Setting interface mode on port &apos;do_convolution/in_stream_V&apos; to &apos;ap_fifo&apos;." tag=""/>
	<Message prefix="[RTGEN 206-500]" severity="INFO" keynum="73" content="Setting interface mode on function &apos;do_convolution&apos; to &apos;ap_ctrl_hs&apos;." tag=""/>
	<Message prefix="[SYN 201-210]" severity="INFO" keynum="402" content="Renamed object name &apos;do_convolution_line_buf_0&apos; to &apos;do_convolution_libkb&apos; due to the length limit 20" tag=""/>
	<Message prefix="[SYN 201-210]" severity="INFO" keynum="402" content="Renamed object name &apos;do_convolution_line_buf_1&apos; to &apos;do_convolution_licud&apos; due to the length limit 20" tag=""/>
	<Message prefix="[RTGEN 206-100]" severity="INFO" keynum="369" content="Finished creating RTL model for &apos;do_convolution&apos;." tag=""/>
	<Message prefix="[HLS 200-111]" severity="INFO" keynum="474" content=" Elapsed time: 0.276 seconds; current allocated memory: 78.761 MB." tag=""/>
	<Message prefix="[RTMG 210-278]" severity="INFO" keynum="RTMG_278_1790" content="Implementing memory &apos;do_convolution_libkb_ram (RAM)&apos; using block RAMs." tag=""/>
	<Message prefix="[HLS 200-111]" severity="INFO" keynum="473" content="Finished generating all RTL models Time (s): cpu = 00:00:03 ; elapsed = 00:00:11 . Memory (MB): peak = 130.641 ; gain = 73.914" tag=""/>
	<Message prefix="[SYSC 207-301]" severity="INFO" keynum="SYSC_301_1065" content="Generating SystemC RTL for do_convolution." tag=""/>
	<Message prefix="[VHDL 208-304]" severity="INFO" keynum="VHDL_304_1066" content="Generating VHDL RTL for do_convolution." tag=""/>
	<Message prefix="[VLOG 209-307]" severity="INFO" keynum="VLOG_307_1067" content="Generating Verilog RTL for do_convolution." tag=""/>
	<Message prefix="[HLS 200-112]" severity="INFO" keynum="472" content="Total elapsed time: 11.267 seconds; peak allocated memory: 78.761 MB." tag=""/>
</Messages>
